demos/__init__.py
demos/dpd/README.md
demos/dpd/__init__.py
demos/dpd/inference.py
demos/dpd/plots_ls.py
demos/dpd/plots_nn.py
demos/dpd/results/constellation_comparison_ls.png
demos/dpd/results/constellation_comparison_nn.png
demos/dpd/results/constellation_data_ls.npz
demos/dpd/results/constellation_data_nn.npz
demos/dpd/results/inference_results_ls.npz
demos/dpd/results/inference_results_nn.npz
demos/dpd/results/loss.npy
demos/dpd/results/ls-dpd-coeff-history.npy
demos/dpd/results/ls-dpd-weights
demos/dpd/results/ls_dpd_convergence.png
demos/dpd/results/nn-dpd-weights
demos/dpd/results/psd_comparison_ls.png
demos/dpd/results/psd_comparison_nn.png
demos/dpd/results/psd_data_ls.npz
demos/dpd/results/psd_data_nn.npz
demos/dpd/results/training_loss.png
demos/dpd/src/__init__.py
demos/dpd/src/config.py
demos/dpd/src/interpolator.py
demos/dpd/src/ls_dpd.py
demos/dpd/src/ls_dpd_system.py
demos/dpd/src/nn_dpd.py
demos/dpd/src/nn_dpd_system.py
demos/dpd/src/power_amplifier.py
demos/dpd/src/rx.py
demos/dpd/src/system.py
demos/dpd/src/tx.py
demos/dpd/tests/README.md
demos/dpd/tests/__init__.py
demos/dpd/tests/test_config.py
demos/dpd/tests/test_interpolator.py
demos/dpd/tests/test_ls_dpd.py
demos/dpd/tests/test_ls_dpd_system.py
demos/dpd/tests/test_nn_dpd.py
demos/dpd/tests/test_nn_dpd_system.py
demos/dpd/tests/test_power_amplifier.py
demos/dpd/tests/test_rx.py
demos/dpd/tests/test_tx.py
demos/dpd/training_ls.py
demos/dpd/training_nn.py
demos/mimo_ofdm_neural_receiver/README.md
demos/mimo_ofdm_neural_receiver/__init__.py
demos/mimo_ofdm_neural_receiver/baseline.py
demos/mimo_ofdm_neural_receiver/inference.py
demos/mimo_ofdm_neural_receiver/plots.py
demos/mimo_ofdm_neural_receiver/results/baseline_results_cdlC.npz
demos/mimo_ofdm_neural_receiver/results/ber_cdlC.png
demos/mimo_ofdm_neural_receiver/results/bler_cdlC.png
demos/mimo_ofdm_neural_receiver/results/inference_results.npz
demos/mimo_ofdm_neural_receiver/results/loss.npy
nextgen_wireless_dl_demos-0.1.2.dist-info/METADATA
nextgen_wireless_dl_demos-0.1.2.dist-info/WHEEL
nextgen_wireless_dl_demos-0.1.2.dist-info/licenses/LICENSE
nextgen_wireless_dl_demos-0.1.2.dist-info/RECORD
