Metadata-Version: 2.4
Name: nextgen-wireless-dl-demos
Version: 0.1.2
Summary: Deep Learning Demos for 5G/6G Using TensorFlow and Sionna
License: MIT
License-File: LICENSE
Author: Srikanth Pagadarai
Author-email: srikanth.pagadarai@gmail.com
Requires-Python: >=3.10,<3.13
Classifier: License :: OSI Approved :: MIT License
Classifier: Programming Language :: Python :: 3
Classifier: Programming Language :: Python :: 3.10
Classifier: Programming Language :: Python :: 3.11
Classifier: Programming Language :: Python :: 3.12
Requires-Dist: matplotlib (>=3.9,<4.0)
Requires-Dist: sionna (>=0.19.0)
